vinery/__init__.py
vinery/dependency_graph.py
vinery/io.py
vinery/tf.py
vinery/cli/arguments.py
vinery/cli/cli.py
vinery/cli/options.py
vinery/cli/options_tf_vars.py
vinery/cli/setup.py
vinery/library/global.tfvars
vinery/library/default/adf/root/data_factory.tf
vinery/library/default/adf/root/variables.tf
vinery/library/default/adls/root/main.tf
vinery/library/default/adls/root/terraform.tfvars
vinery/library/default/adls/root/variables.tf
vinery/library/default/akv/root/key_vault.tf
vinery/library/default/databricks/root/README.md
vinery/library/default/databricks/root/databricks.tf
vinery/library/default/databricks/root/subnets.tf
vinery/library/default/databricks/root/variables.tf
vinery/library/default/databricks/unity-catalog/_deps.conf
vinery/library/default/databricks/unity-catalog/main.tf
vinery/library/default/modules/azuread-databricks/main.tf
vinery/library/default/modules/azuread-databricks/outputs.tf
vinery/library/default/modules/azuread-databricks/variables.tf
vinery/library/default/modules/azurerm-adf_linked_services/adls.tf
vinery/library/default/modules/azurerm-adf_linked_services/databricks.tf
vinery/library/default/modules/azurerm-adf_linked_services/key_vault.tf
vinery/library/default/modules/azurerm-adf_linked_services/network.tf
vinery/library/default/modules/azurerm-adf_linked_services/variables.tf
vinery/library/default/modules/azurerm-dbw_private_link/private_dns_zone.tf
vinery/library/default/modules/azurerm-dbw_private_link/private_endpoints.tf
vinery/library/default/modules/azurerm-dbw_private_link/variables.tf
vinery/library/default/root/_deps.conf
vinery/library/default/root/main.tf
vinery/library/default/root/outputs.tf
vinery/library/default/root/terraform.tf
vinery/library/default/root/variables.tf
vinery/library/default/root/virtual_network.tf
vinery-0.1.0.dist-info/entry_points.txt
vinery-0.1.0.dist-info/WHEEL
vinery-0.1.0.dist-info/METADATA
vinery-0.1.0.dist-info/RECORD
