Metadata-Version: 2.1
Name: vinery
Version: 0.1.0
Summary: CLI tool for building modular infrastructure
Requires-Python: >=3.10
Requires-Dist: click>=8.1.8
Requires-Dist: networkx>=3.4.2
Requires-Dist: matplotlib
Requires-Dist: pytest >=2.7.3 ; extra == "test"
Provides-Extra: test
